hg2_data_extractor/__init__.py
hg2_data_extractor/__main__.py
hg2_data_extractor/bundle_patch.py
hg2_data_extractor/cli.py
hg2_data_extractor/config.py
hg2_data_extractor/data_cipher.py
hg2_data_extractor/data_downloader.py
hg2_data_extractor/data_extractor.py
hg2_data_extractor/enums.py
hg2_data_extractor/exceptions.py
hg2_data_extractor/types.py
hg2_data_extractor-0.7.0.dist-info/METADATA
hg2_data_extractor-0.7.0.dist-info/WHEEL
hg2_data_extractor-0.7.0.dist-info/entry_points.txt
hg2_data_extractor-0.7.0.dist-info/licenses/LICENSE
hg2_data_extractor-0.7.0.dist-info/RECORD
