Metadata-Version: 2.4
Name: hg2-data-extractor
Version: 0.7.0
Summary: Python package for extracting Houkai Gakuen 2 assets data
License-File: LICENSE
Requires-Python: <4.0,>=3.12
Requires-Dist: pycryptodome<4.0.0,>=3.21.0
Requires-Dist: pydantic-settings<3.0.0,>=2.6.1
Requires-Dist: requests<3.0.0,>=2.32.3
Requires-Dist: tqdm<5.0.0,>=4.66.5
Requires-Dist: typer<1.0.0,>=0.12.5
Requires-Dist: unitypy<2.0.0,>=1.20.4
